azure/durable_functions/__init__.py
azure/durable_functions/constants.py
azure/durable_functions/entity.py
azure/durable_functions/orchestrator.py
azure/durable_functions/decorators/__init__.py
azure/durable_functions/decorators/durable_app.py
azure/durable_functions/decorators/metadata.py
azure/durable_functions/models/DurableEntityContext.py
azure/durable_functions/models/DurableHttpRequest.py
azure/durable_functions/models/DurableOrchestrationBindings.py
azure/durable_functions/models/DurableOrchestrationClient.py
azure/durable_functions/models/DurableOrchestrationContext.py
azure/durable_functions/models/DurableOrchestrationStatus.py
azure/durable_functions/models/EntityStateResponse.py
azure/durable_functions/models/FunctionContext.py
azure/durable_functions/models/OrchestrationRuntimeStatus.py
azure/durable_functions/models/OrchestratorState.py
azure/durable_functions/models/PurgeHistoryResult.py
azure/durable_functions/models/ReplaySchema.py
azure/durable_functions/models/RetryOptions.py
azure/durable_functions/models/RpcManagementOptions.py
azure/durable_functions/models/Task.py
azure/durable_functions/models/TaskOrchestrationExecutor.py
azure/durable_functions/models/TokenSource.py
azure/durable_functions/models/__init__.py
azure/durable_functions/models/actions/Action.py
azure/durable_functions/models/actions/ActionType.py
azure/durable_functions/models/actions/CallActivityAction.py
azure/durable_functions/models/actions/CallActivityWithRetryAction.py
azure/durable_functions/models/actions/CallEntityAction.py
azure/durable_functions/models/actions/CallHttpAction.py
azure/durable_functions/models/actions/CallSubOrchestratorAction.py
azure/durable_functions/models/actions/CallSubOrchestratorWithRetryAction.py
azure/durable_functions/models/actions/CompoundAction.py
azure/durable_functions/models/actions/ContinueAsNewAction.py
azure/durable_functions/models/actions/CreateTimerAction.py
azure/durable_functions/models/actions/NoOpAction.py
azure_functions_durable-1.4.0.dist-info/LICENSE
azure_functions_durable-1.4.0.dist-info/METADATA
azure_functions_durable-1.4.0.dist-info/WHEEL
azure_functions_durable-1.4.0.dist-info/top_level.txt
azure_functions_durable-1.4.0.dist-info/RECORD
