Metadata-Version: 2.1
Name: azure-functions-durable
Version: 1.4.0
Summary: Durable Functions For Python
Home-page: https://github.com/Azure/azure-functions-durable-python
Author: Azure Functions team at Microsoft Corp.
Author-email: azurefunctions@microsoft.com
License: MIT
Keywords: azure functions azurefunctions python serverless workflows durablefunctions
Platform: UNKNOWN
Classifier: License :: OSI Approved :: MIT License
Classifier: Intended Audience :: Developers
Classifier: Programming Language :: Python :: 3
Classifier: Operating System :: Microsoft :: Windows
Classifier: Operating System :: POSIX
Classifier: Operating System :: MacOS :: MacOS X
Classifier: Environment :: Web Environment
Classifier: Development Status :: 5 - Production/Stable
Requires-Python: >=3.9,<4
License-File: LICENSE
